music_code/__init__.py
music_code/analytics.py
music_code/chordnet.py
music_code/music_code.py
music_code/sql_kit.py
music_code-0.0.20.dist-info/LICENSE.txt
music_code-0.0.20.dist-info/METADATA
music_code-0.0.20.dist-info/WHEEL
music_code-0.0.20.dist-info/top_level.txt
music_code-0.0.20.dist-info/RECORD
