Metadata-Version: 2.1
Name: music-code
Version: 0.0.20
Summary: Python library for creating music
Home-page: https://github.com/wesleyLaurence
Author: Wesley Laurence and Henry Franklin
Author-email: wesleylaurencetech@gmail.com
License: UNKNOWN
Platform: UNKNOWN
Classifier: Programming Language :: Python :: 3
Classifier: License :: OSI Approved :: MIT License
Classifier: Operating System :: OS Independent
Requires-Python: >=3.6
Requires-Dist: numpy
Requires-Dist: pandas
Requires-Dist: matplotlib
Requires-Dist: seaborn
Requires-Dist: soundfile
Requires-Dist: scipy
Requires-Dist: sklearn
Requires-Dist: datetime
Requires-Dist: pyaudio
Requires-Dist: wave
Requires-Dist: mysql-connector-python
